base64perf/__init__.py
base64perf/base64c.cpython-310-darwin.so
base64perf/base64perf.c
base64perf/base64perf.cpython-310-darwin.so
base64perf/base64perf.pyi
base64perf-0.0.11.dist-info/licenses/LICENSE
base64perf-0.0.11.dist-info/METADATA
base64perf-0.0.11.dist-info/WHEEL
base64perf-0.0.11.dist-info/top_level.txt
base64perf-0.0.11.dist-info/RECORD
